[
{"nombre": "Laptop/Notebook Lenovo S145-15Ast Slim Amd A9-9425 3.1 GHz-8Gb-1Tb-Tg2Gb Radeon-No Dvd-Gris-15", "precio_regular": 481.08, "precio_oferta": 333.65, "categoria": "Laptos", "empresa": "Computron"},
{"nombre": "Laptop/Notebook Hp Amd R5-2500U 2.0 Ghz-16Gb-1Tb-No Dvd-15.6.", "precio_regular": 143.16, "precio_oferta": 104.21, "categoria": "Laptos", "empresa": "Computron"},
{"nombre": "LAPTOP/NOTEBOOK LENOVO IP330-14IKB CI3 7020U 2.3-GHZ-4GB-1TB-NO DVD-14- GRIS-W10", "precio_regular": 725.89, "precio_oferta": 593.89.41, "categoria": "Laptos", "empresa": "Point"},
{"nombre": "Laptop/Notebook Hp Amd R5-2500U 2.0", "precio_regular": 881.47, "precio_oferta": 771.17, "categoria": "Laptos", "empresa": "Point"},
{"nombre": "Laptop HP 14-CK0010LA | Intel Core i7-7020U", "precio_regular": 559.92, "precio_oferta": 420.87, "categoria": "Laptos", "empresa": "Point"},
{"nombre": "Laptop Lenovo S145-14IWL", "precio_regular": 389.54, "precio_oferta": 345.26, "categoria": "Laptos", "empresa": "Point"},
{"nombre": "Laptop HP 14-CK0010LA | Intel Core i3-7020U", "precio_regular": 529.13, "precio_oferta": 466.8, "categoria": "Laptos", "empresa": "Point"},
{"nombre": "Laptop HP 15-DB1022LA 3, 8GB, 1TB, 15", "precio_regular": 286.82, "precio_oferta": 223.44, "categoria": "Laptos", "empresa": "Computron"},
{"nombre": "Laptop HP 15-CM1002LA AMD Ryzen 5 3500U", "precio_regular": 570.29, "precio_oferta": 490.71, "categoria": "Laptos", "empresa": "Point"},
{"nombre": "Laptop HP 13-CM1002LA", "precio_regular": 721.68, "precio_oferta": 606.98, "categoria": "Laptos", "empresa": "Computron"},
{"nombre": "LAPTOP/NOTEBOOK LENOVO S145-14IGM SLIM CELERON N4000 1.1GHZ-4GB-1TB-NO DVD-GRIS-14", "precio_regular": 404.45, "precio_oferta": 394.43, "categoria": "Laptos", "empresa": "Point"},
{"nombre": "Laptop/Notebook Hp Ci7 7500U 2.7Ghz-8Gb-1Tb-Tg Mx130 4Gb-Dvd-15.6", "precio_regular": 1,034.82 , "precio_oferta": 934.82 , "categoria": "Laptos", "empresa": "Computron"},
{"nombre": "Laptop HP 15-DB1022LA AMD Ryzen 3, 8GB, 1TB, 15", "precio_regular": 623.61, "precio_oferta": 570.07, "categoria": "Laptos", "empresa": "Computron"},
{"nombre": "Laptop DELL 5593 | Intel i7-1065G7 ", "precio_regular": 427.37, "precio_oferta": 335.05, "categoria": "Laptos", "empresa": "Computron"},
{"nombre": "Laptop/Notebook Hp Envy X360 Amd", "precio_regular": 597.87, "precio_oferta": 233.53, "categoria": "Laptos", "empresa": "Computron"},
{"nombre": "Laptop DELL 5593 | Intel i3-1015H ", "precio_regular": 497.16, "precio_oferta": 311.37, "categoria": "Laptos", "empresa": "Computron"},
{"nombre": "Laptop/Notebook Hp Amd R5-2500U 2.0 Ghz-16Gb-1Tb-No Dvd-15.6", "precio_regular": 141.03, "precio_oferta": 110.56, "categoria": "Laptos", "empresa": "Computron"},
{"nombre": "Laptop/Notebook Hp Envy X360 Amd R5-2500U 2.0Ghz-8Gb-256Gb Ssd-13", "precio_regular": 92.08, "precio_oferta": 80.43, "categoria": "Laptos", "empresa": "Computron"},
{"nombre": "Laptop/Notebook Hp Amd R5-2500U 2.0 Ghz-16Gb-1Tb-No ", "precio_regular": 59.74, "precio_oferta": 40.14, "categoria": "Laptos", "empresa": "Computron"},
{"nombre": "LAPTOP/NOTEBOOK LENOVO IP330-14IKB ", "precio_regular": 183.95, "precio_oferta": 123.61, "categoria": "Laptos", "empresa": "Computron"},
{"nombre": "Impresora Multifuncion Hp Color Ink 2135 Blanca 20Ppn, 16Ppc", "precio_regular": 559.0, "precio_oferta": 457.03, "categoria": "Impresoras", "empresa": "Computron"},
{"nombre": "Impresora Multifuncion Hp Color Ink 5201 Negro 20Ppn, 16Ppc", "precio_regular": 290.47, "precio_oferta": 217.96, "categoria": "Impresoras", "empresa": "Computron"},
{"nombre": "Impresora Multifuncion Hp Color Ink 3012 Gris 20Ppn, 16Ppc", "precio_regular": 541.13, "precio_oferta": 472.72, "categoria": "Impresoras", "empresa": "Computron"},
{"nombre": "LAPTOP/NOTEBOOK LENOVO IP330-14IKB ", "precio_regular": 62.89, "precio_oferta": 54.93, "categoria": "Televisores", "empresa": "Computron"},
{"nombre": "Celular Samsung J2 Core 5 1Gb 8Gb Negro", "precio_regular": 198.99, "precio_oferta": 198.99, "categoria": "celulares", "empresa": "Computron"},
{"nombre": "Celular Samsung A50 Negro 6.4": 398.99, "precio_oferta": 198.99, "categoria": "celulares", "empresa": "Computron"},
{"nombre": "Celular Samsung": 198.99, "precio_oferta": 198.99, "categoria": "celulares", "empresa": "Point"},
{"nombre": "Celular Samsung A30 Negro 6,4 3Gb 32Gb Ds", "precio_regular": 547.0, "precio_oferta": 447.0, "categoria": "celulares", "empresa": "Point"},
{"nombre": "Celular Samsung A30 Azul 6,4", "precio_regular": 568.99, "precio_oferta": 468.99, "categoria": "celulares", "empresa": "Computron"},
{"nombre": "Celular Samsung A30 Blanco 5,4 3Gb 32Gb Ds", "precio_regular": 468.99, "precio_oferta": 368.99, "categoria": "celulares", "empresa": "Point"},
{"nombre": "Celular Samsung Galaxy A10S 6.2", "precio_regular": 198.99, "precio_oferta": 98.99, "categoria": "celulares", "empresa": "Point"},
{"nombre": "Celular Samsung Galaxy 6.1", "precio_regular": 189.0, "precio_oferta": 189.0, "categoria": "celulares", "empresa": "Point"},
{"nombre": "Celular Huawei Y5 2019 32Gb Azul", "precio_regular": 148.99, "precio_oferta": 148.99, "categoria": "celulares", "empresa": "Computron"},
{"nombre": "Celular Samsung Galaxy", "precio_regular": 298.99, "precio_oferta": 298.99, "categoria": "celulares", "empresa": "Point"},
{"nombre": "Celular Huawei Y5 2019 32Gb Negro", "precio_regular": 329.0, "precio_oferta": 329.0, "categoria": "celulares", "empresa": "Computron"},
{"nombre": "Celular Xiaomi Redmi 8A. 2Gb 32Gb. Negro Agregar Plu-2-Pin", "precio_regular": 399.0, "precio_oferta": 399.0, "categoria": "celulares", "empresa": "Computron"},
{"nombre": "Celular Samsung Galaxy", "precio_regular": 119.0, "precio_oferta": 119.0, "categoria": "celulares", "empresa": "Point"},
{"nombre": "Celular Huawei Y5 2019 32Gb Blanco", "precio_regular": 128.99, "precio_oferta": 128.99, "categoria": "celulares", "empresa": "Computron"},
{"nombre": "Celular Xiaomi Redmi 8A. 2Gb 32Gb. Blanco Agregar Plu-2-Pin", "precio_regular": 108.99, "precio_oferta": 108.99, "categoria": "celulares", "empresa": "Point"},
{"nombre": "Celular Huawei Y5 2019 32Gb Gris", "precio_regular": 24.89, "precio_oferta": 24.89, "categoria": "celulares", "empresa": "Computron"},
{"nombre": "Celular Samsung Galaxy A80 6.7", "precio_regular": 278.99, "precio_oferta": 178.99, "categoria": "celulares", "empresa": "Point"},
{"nombre": "Celular Xiaomi Redmi 8A. 2Gb 32Gb. Azul Agregar Plu-2-Pin", "precio_regular": 98.99, "precio_oferta": 98.99, "categoria": "celulares", "empresa": "Computron"},
{"nombre": "Celular Huawei Y5 2019 32Gb Blanco", "precio_regular": 98.99, "precio_oferta": 98.99, "categoria": "celulares", "empresa": "Point"},
{"nombre": "Celular Samsung J2 Core 5", "precio_regular": 108.99, "precio_oferta": 108.99, "categoria": "celulares", "empresa": "Point"},
{"nombre": "Celular Huawei Y5 2019 32Gb Gris", "precio_regular": 248.99, "precio_oferta": 248.99, "categoria": "celulares", "empresa": "Point"},
{"nombre": "Celular Huawei Y5 2019 32Gb Negro", "precio_regular": 248.99, "precio_oferta": 248.99, "categoria": "celulares", "empresa": "Point"},
{"nombre": "Celular Huawei Y5 2019 32Gb Blanco", "precio_regular": 198.99, "precio_oferta": 198.99, "categoria": "celulares", "empresa": "Point"},
{"nombre": "Celular Samsung A20s", "precio_regular": 169.98, "precio_oferta": 169.98, "categoria": "celulares", "empresa": "Point"},
{"nombre": "Celular Mtt M14D Gsm Bluetooth", "precio_regular": 35.0, "precio_oferta": 35.0, "categoria": "celulares", "empresa": "Point"},
{"nombre": "Celular Mtt M15D Gsm Bluetooth", "precio_regular": 35.0, "precio_oferta": 35.0, "categoria": "celulares", "empresa": "Point"},
{"nombre": "Xtratech Intel Ci3 9Na 3.6GHz/4Gb/1Tb/1Gb Vga/Dvdwr/Tmp/W10 Golden Dorado", "precio_regular": 119.98, "precio_oferta": 119.98, "categoria": "celulares", "empresa": "Point"},
{"nombre": "Xtratech Intel Ci3 9Na 3.6GHz/4Gb/1Tb/1Gb Vga/Dvdwr/Tmp/W10 Classic Blanco", "precio_regular": 99.98, "precio_oferta": 99.98, "categoria": "celulares", "empresa": "Point"},
{"nombre": "Xtratech Intel Ci5 8Va 2.8GHz/8Gb/1Tb/Dvdwr/Tmp Elegant Dorado", "precio_regular": 169.98, "precio_oferta": 169.98, "categoria": "celulares", "empresa": "Point"},
{"nombre": "Xtratech Intel Ci5 8Va 2.8GHz/8Gb/1Tb/Dvdwr/Tmp Vari Met\u00e1lico", "precio_regular": 149.97, "precio_oferta": 149.97, "categoria": "celulares", "empresa": "Point"},
{"nombre": "Computador Aio Lenovo A340-22Iwl Ci5-8265U-4Gb-1Tb-No Dvd-21.5", "precio_regular": 175.0, "precio_oferta": 175.0, "categoria": "Computadora Escritorio", "empresa": "Point"},
{"nombre": "Computador Aio Lenovo A340-22Iwl Ci5-8265U-4Gb-1Tb-No Dvd-21.5Quality Beige 1.5 Plazas", "precio_regular": 105.0, "precio_oferta": 105.0, "categoria": "Computadora Escritorio", "empresa": "Point"},
{"nombre": "Computador Aio Lenovo A340-22Iwl Ci5-8265U-4Gb-1Tb-No Dvd-21.5Tapiz Gris 3 Plazas", "precio_regular": 284.99, "precio_oferta": 284.99, "categoria": "Computadora Escritorio", "empresa": "Point"},
{"nombre": "Computador Aio Lenovo A340-22Iwl Ci5-8265U-4Gb-1Tb-No Dvd-21.5Tapiz Gris 2.5 Plazas", "precio_regular": 178.99, "precio_oferta": 178.99, "categoria": "Computadora Escritorio", "empresa": "Point"},
{"nombre": "Ottoman de Cuerina Negro", "precio_regular": 24.89, "precio_oferta": 24.89, "categoria": "celulares", "empresa": "Point"},
{"nombre": "Xtratech Intel Ci5 8Va 2.8GHz/8Gb/1Tb/Dvdwr/Tmp Oslo", "precio_regular": 158.99, "precio_oferta": 158.99, "categoria": "celulares", "empresa": "Point"},
{"nombre": "Xtratech Intel Ci5 8Va 2.8GHz/8Gb/1Tb/Dvdwr/Tmp Parma", "precio_regular": 148.99, "precio_oferta": 148.99, "categoria": "celulares", "empresa": "Point"},
{"nombre": "Computador Aio Lenovo A340-22Iwl Ci5-8265U-4Gb-1Tb-No Dvd-21.5Tapiz Gris 2 Plazas", "precio_regular": 154.99, "precio_oferta": 154.99, "categoria": "Computadora Escritorio", "empresa": "Point"},
{"nombre": "Computador Aio Lenovo A340-22Iwl Ci5-8265U-4Gb-1Tb-No Dvd-21.5Tapiz Gris 1.5 Plazas", "precio_regular": 134.99, "precio_oferta": 134.99, "categoria": "Computadora Escritorio", "empresa": "Point"},
{"nombre": "Computador Dell Vostr", "precio_regular": 168.99, "precio_oferta": 168.99, "categoria": "Computadora Escritorio", "empresa": "Point"},
{"nombre": "Computador Dell Vostro 3470 Ci7 8700 3.20Ghz-8Gb-1Tb-Dvd-Blanco-T/M-W10 Pro", "precio_regular": 1158.99, "precio_oferta": 1148.99, "categoria": "Computadora Escritorio", "empresa": "Point"},
{"nombre": "Computador Dell Vostro Negra-T/M-W10 Pro", "precio_regular": 2298.99, "precio_oferta": 2298.99, "categoria": "Computadora Escritorio", "empresa": "Point"},
{"nombre": "Computador Aio Lenovo 330-20Igm Celeron J4005 2.00 GHz-4Gb-1Tb-Dvd-19.6-Blanca-W10 3 Plazas", "precio_regular": 334.99, "precio_oferta": 334.99, "categoria": "Computadora Escritorio", "empresa": "Point"},
{"nombre": "Computador Aio Lenovo 330-20Igm Celeron J4005 2.00 GHz-4Gb-1Tb-Dvd-19.6-Negro-W10 2.5 Plazas", "precio_regular": 245.0, "precio_oferta": 245.0, "categoria": "Computadora Escritorio", "empresa": "Point"},
{"nombre": "Computador Aio Lenovo 330-20Igm Celeron J4005 2.00 GHz-4Gb-1Tb-Dvd-19.6-Gris-W10 2 Plazas", "precio_regular": 224.99, "precio_oferta": 224.99, "categoria": "Computadora Escritorio", "empresa": "Point"},
{"nombre": "Xtratech Pentium 8Va Gen 3.7GHz/4Gb de Lujo Non Flip Beige 3 Plazas", "precio_regular": 469.0, "precio_oferta": 469.0, "categoria": "Computadora Escritorio", "empresa": "Point"},
{"nombre": "Xtratech Pentium 8Va Gen 3.7GHz/4Gb de Lujo Non Flip Beige 2.5 Plazas", "precio_regular": 364.99, "precio_oferta": 364.99, "categoria": "Computadora Escritorio", "empresa": "Point"},
{"nombre": "Xtratech Pentium 8Va Gen 3.7GHz/4Gb de Lujo Non Flip Beige 2 Plazas", "precio_regular": 298.99, "precio_oferta": 298.99, "categoria": "Computadora Escritorio", "empresa": "Point"},
{"nombre": "Xtratech Pentium 8Va Gen 3.7GHz/4Gb de Lujo Non Flip Beige 1.5 Plazas", "precio_regular": 238.99, "precio_oferta": 238.99, "categoria": "Computadora Escritorio", "empresa": "Point"},
{"nombre": "Xtratech Pentium 8Va Gen 3.7GHz/4Gb de Lujo Non Flip Gris 3 Plazas", "precio_regular": 469.0, "precio_oferta": 469.0, "categoria": "Computadora Escritorio", "empresa": "Point"},
{"nombre": "Xtratech Pentium 8Va Gen 3.7GHz/4Gb de Lujo Non Flip Gris 2 Plazas", "precio_regular": 298.99, "precio_oferta": 298.99, "categoria": "Computadora Escritorio", "empresa": "Point"},
{"nombre": "Xtratech Pentium 7Va Gen 2.7GHz/8Gb Gold  ", "precio_regular": 698.99, "precio_oferta": 698.99, "categoria": "Computadora Escritorio", "empresa": "Point"},
{"nombre": "Xtratech Pentium 7Va Gen 2.7GHz/8Gb Gold ", "precio_regular": 560.0, "precio_oferta": 560.0, "categoria": "Computadora Escritorio", "empresa": "Point"},
{"nombre": "Xtratech Pentium 7Va Gen 2.7GHz/8Gb Gold  ", "precio_regular": 448.99, "precio_oferta": 448.99, "categoria": "Computadora Escritorio", "empresa": "Point"},
{"nombre": "Computador Aio Lenovo 520-22Ast Amd_A9-9420-8Gb-1Tb - No Dvd -21.5 Grand Palais 2.5 Plazas", "precio_regular": 918.99, "precio_oferta": 918.99, "categoria": "Computadora Escritorio", "empresa": "Point"},
{"nombre": "Computador Aio Lenovo 520-22Ast Amd_A9-9420-8Gb-1Tb - No Dvd -21.5 Caressa 3 Plazas", "precio_regular": 1.0, "precio_oferta": 1.0, "categoria": "Computadora Escritorio", "empresa": "Point"},
{"nombre": "Computador Aio Lenovo 520-22Ast Amd_A9-9420-8Gb-1Tb - No Dvd -21.5 Caressa 2.5 Plazas", "precio_regular": 1.0, "precio_oferta": 1.0, "categoria": "Computadora Escritorio", "empresa": "Point"},
{"nombre": "Computador Aio Lenovo 520-22Ast Amd 5 Estrellas Gris 2.5 Plazas", "precio_regular": 368.99, "precio_oferta": 368.99, "categoria": "Computadora Escritorio", "empresa": "Point"},
{"nombre": "Computador Aio Lenovo 520-22Ast Amd Aniversario 2.5 Plazas", "precio_regular": 248.99, "precio_oferta": 248.99, "categoria": "Computadora Escritorio", "empresa": "Point"},
{"nombre": "Televisor-Tv Samsung 32 Led Hd 720P Smart Wifi (1A) Rojo", "precio_regular": 518.49, "precio_oferta": 418.49, "categoria": "Televisores", "empresa": "Point"},
{"nombre": "Televisor-Tv Samsung 12 Led Hd 720P Smart Wifi (1A) Blanco", "precio_regular": 618.49, "precio_oferta": 418.49, "categoria": "Televisores", "empresa": "Point"},
{"nombre": "Televisor-Tv Samsung 64", "precio_regular": 248.99, "precio_oferta": 248.99, "categoria": "Televisores", "empresa": "Point"},
{"nombre": "Televisor-Tv Xtratech 32  Led Hd Smart 720 Wifi Isdb-T Napoli Gris 8 Puestos", "precio_regular": 998.99, "precio_oferta": 998.99, "categoria": "Televisores", "empresa": "Point"},
{"nombre": "Televisor-Tv Xtratech 32  Led Hd Smart 720 Wifi Isdb-T Danna 6 Sillas", "precio_regular": 749.0, "precio_oferta": 749.0, "categoria": "Televisores", "empresa": "Point"},
{"nombre": "Televisor-Tv Xtratech Wifi Isdb-T", "precio_regular": 598.99, "precio_oferta": 598.99, "categoria": "Televisores", "empresa": "Point"},
{"nombre": "Televisor-Tv Xtratech 64", "precio_regular": 78.99, "precio_oferta": 78.99, "categoria": "Televisores", "empresa": "Point"},
{"nombre": "Televisor-Tv Samsung 55  Led 4K Uhd Smart (2A) - Soundbar 4 Puestos", "precio_regular": 148.99, "precio_oferta": 148.99, "categoria": "Televisores", "empresa": "Point"},
{"nombre": "Televisor-Tv Samsung 65  Led 4K Uhd Smart (2A) - Soundbar Niza 4 puestos", "precio_regular": 218.99, "precio_oferta": 218.99, "categoria": "Televisores", "empresa": "Point"},
{"nombre": "Televisor-Tv Samsung 55 Led 4K Uhd Smart (2A)", "precio_regular": 1118.49, "precio_oferta": 1118.49, "categoria": "Televisores", "empresa": "Point"},
{"nombre": "Televisor-Tv Samsung 75  Led 4K Uhd Smart (2A) - Soundbar Ferrara Naranja 6 Puestos", "precio_regular": 668.99, "precio_oferta": 668.99, "categoria": "Televisores", "empresa": "Point"},
{"nombre": "Televisor-Tv Samsung 65  Led 4K Uhd Smart (2A) - Soundbar Tivolli 6 Puestos", "precio_regular": 698.99, "precio_oferta": 698.99, "categoria": "Televisores", "empresa": "Point"},
{"nombre": "Televisor-Tv Samsung 55  Led 4K Uhd Smart (2A) - Soundbar Luciana 6 Puestos", "precio_regular": 698.99, "precio_oferta": 698.99, "categoria": "Televisores", "empresa": "Point"},
{"nombre": "Televisor-Tv Samsung 75  Led 4K Uhd Smart (2A) - Soundbar Trevi 6 Puestos", "precio_regular": 679.0, "precio_oferta": 679.0, "categoria": "Televisores", "empresa": "Point"},
{"nombre": "Televisor-Tv Samsung 65  Led 4K Uhd Smart (2A) - Soundbar Atlantis 6 Puestos", "precio_regular": 598.99, "precio_oferta": 598.99, "categoria": "Televisores", "empresa": "Point"},
{"nombre": "Televisor-Tv Samsung 55  Led 4K Uhd Smart (2A) - Soundbar Bruselas 6 Puestos", "precio_regular": 798.99, "precio_oferta": 798.99, "categoria": "Televisores", "empresa": "Point"},
{"nombre": "Televisor-Tv Samsung 65  Led 4K Uhd Smart (2A) - Soundbar Bruselas 6 Puestos Terracota", "precio_regular": 798.99, "precio_oferta": 798.99, "categoria": "Televisores", "empresa": "Point"},
{"nombre": "Televisor-Tv Samsung 55  Led 4K Uhd Smart (2A) - Soundbar Golden 6 Puestos Caf\u00e9", "precio_regular": 848.99, "precio_oferta": 848.99, "categoria": "Televisores", "empresa": "Point"},
{"nombre": "Televisor-Tv Tcl 43 Led 4K Uhd Smart Wifi (1A)", "precio_regular": 918.49, "precio_oferta": 818.49, "categoria": "Televisores", "empresa": "Point"},
{"nombre": "Televisor-Tv Samsung 55 Led 4K Uhd Smart (2A)", "precio_regular": 818.49, "precio_oferta": 718.49, "categoria": "Televisores", "empresa": "Point"},
{"nombre": "Televisor-Tv Samsung 65 Led 4K Uhd Smart (2A)", "precio_regular": 778.99, "precio_oferta": 678.99, "categoria": "Televisores", "empresa": "Point"},
{"nombre": "Televisor-Tv Samsung 85 Led 4K Uhd Smart (2A)", "precio_regular": 678.99, "precio_oferta": 578.99, "categoria": "Televisores", "empresa": "Point"},
{"nombre": "Televisor-Tv Samsung 55 Led 4K Uhd Smart (2A)", "precio_regular": 548.99, "precio_oferta": 448.99, "categoria": "Televisores", "empresa": "Point"},
{"nombre": "Televisor-Tv Samsung 55  Led 4K Uhd Smart (2A) - Soundbar Cino Caf\u00e9 6 Puestos", "precio_regular": 478.99, "precio_oferta": 478.99, "categoria": "Televisores", "empresa": "Point"},
{"nombre": "Televisor-Tv Samsung 65  Led 4K Uhd Smart (2A) - Soundbar Blu 4 Lugares", "precio_regular": 179.89, "precio_oferta": 179.89, "categoria": "Televisores", "empresa": "Point"},
{"nombre": "Televisor-Tv Samsung 50  Led 4K Uhd Smart (2A) - Soundbar Tess 4 Puestos Caf\u00e9", "precio_regular": 218.99, "precio_oferta": 218.99, "categoria": "Televisores", "empresa": "Point"},
{"nombre": "Televisor-Tv Samsung 75  Led 4K Uhd Smart (2A) - Soundbar Essen 6 Puestos", "precio_regular": 428.99, "precio_oferta": 428.99, "categoria": "Televisores", "empresa": "Point"},
{"nombre": "Televisor-Tv Samsung 55  Led 4K Uhd Smart (2A) - Soundbar Triangular 6 Puestos Caf\u00e9", "precio_regular": 598.99, "precio_oferta": 598.99, "categoria": "Televisores", "empresa": "Point"},
{"nombre": "Televisor-Tv Samsung 55  Led 4K Uhd Smart (2A) - Soundbar Anya 4 puestos", "precio_regular": 179.89, "precio_oferta": 179.89, "categoria": "Televisores", "empresa": "Point"},
{"nombre": "Televisor-Tv Tcl 43 Led 4K Uhd Smart Wifi (1A)", "precio_regular": 598.99, "precio_oferta": 598.99, "categoria": "Televisores", "empresa": "Point"},
{"nombre": "Televisor-Tv Samsung 55 - Soundbar Triangular 6 Puestos Rojo", "precio_regular": 598.99, "precio_oferta": 598.99, "categoria": "Televisores", "empresa": "Point"},
{"nombre": "Televisor-Tv Samsung 55 - Soundbar Triangular 6 Puestos Negro", "precio_regular": 598.99, "precio_oferta": 598.99, "categoria": "Televisores", "empresa": "Point"}
]